minillmflow/__init__.py
minillmflow-0.0.5.dist-info/LICENSE
minillmflow-0.0.5.dist-info/METADATA
minillmflow-0.0.5.dist-info/WHEEL
minillmflow-0.0.5.dist-info/top_level.txt
minillmflow-0.0.5.dist-info/RECORD
