Metadata-Version: 2.1
Name: minillmflow
Version: 0.0.5
Summary: A Minimalist Framework for LLM Workflows in 100 Lines of Code
Home-page: https://github.com/zachary62/miniLLMFlow
Author: Zachary Huang
Author-email: zh2408@columbia.edu
License-File: LICENSE
